{
  "tenantId": "dj",
  "moduleName": "tenant",
  "tenants": [
    {
      "code": "dj",
      "name": "Djibouti",
      "description": "Djibouti",
      "logoId": "https://egov-bucket.s3.af-south-1.amazonaws.com/DATUH.jpeg",
      "imageId": "",
      "domainUrl": "https://www.presidence.dj/",
      "type": "CITY",
      "twitterUrl": "",
      "facebookUrl": "",
      "emailId": "dj.state@gmail.com",
      "OfficeTimings": {
        "Mon - Fri": "9.00 AM - 5.00 PM"
      },
      "city": {
        "name": "Djibouti",
        "localName": "",
        "districtCode": "dj",
        "districtName": "",
        "districtTenantCode": "dj",
        "regionName": "",
        "ulbGrade": "Minister of the City, Urban Planning and Housing",
        "longitude": 75.3412,
        "latitude": 31.1471,
        "shapeFileLocation": "",
        "captcha": "",
        "code": "0",
        "ddrName": ""
      },
      "address": "Minister of the City, Urban Planning and Housing",
      "contactNumber": "+253 21 35 60 34"
    }
  ]
}
